{
  "event_id": "evt_43f38dd8018f",
  "task_id": "task_e88e3b75a521",
  "event_type": "checkpoint_recorded",
  "actor": "executor",
  "lane": "executor",
  "created_at": "2026-03-08T05:40:50.202689+00:00",
  "from_status": null,
  "to_status": null,
  "checkpoint_summary": "Executor started work on: build the minimum durable runtime spine",
  "reason": null,
  "final_outcome": null,
  "artifact_id": null,
  "artifact_type": null,
  "artifact_title": null,
  "already_linked": null,
  "version": "v1"
}
